password_generator.py
gen_passwrd-0.1.dist-info/METADATA
gen_passwrd-0.1.dist-info/WHEEL
gen_passwrd-0.1.dist-info/top_level.txt
gen_passwrd-0.1.dist-info/RECORD
