Metadata-Version: 2.1
Name: gen-passwrd
Version: 0.1
Summary: A simple password generator using existing tools
Author: Farid Abdi
Author-email: farid.abdi.cs@gmail.com
